Workbook

Sheet Resumen
A1: RESUMEN CONCILIACIÓN - Web
A2: INSTRUMENTAL PASTEUR SRL Desde: 28/02/26
A4: Saldo Anterior s/ Banco | B4: 5622491.5 | D4: Estado de la descarga del Extracto.
A5: (+) Total Debe Mayor Sistema | B5: =+'2. Auditoría Sistema'!E7 -> 0 | D5: Saldo inicio | E5: =+'1. Auditoría Banco'!B3 -> 0
A6: (-) Total Haber Mayor Sistema | B6: =+'2. Auditoría Sistema'!F7 -> 0 | D6: Creditos | E6: =+'1. Auditoría Banco'!D7 -> 0
A7: (=) Saldo Final Calculado | B7: =+B4+B5-B6 -> 5622491.5 | D7: Debitos | E7: =+'1. Auditoría Banco'!C7 -> 0
A8: Credito Banco no conciliado | B8: =+'4. Conciliación'!E17 -> 0 | D8: Saldo final | E8: =+E5+E6-E7 -> 0
A9: Debito Banco No conciliado | B9: =+'4. Conciliación'!D17 -> 0
A10: Debe Sistema no conciliado | B10: =+'4. Conciliación'!D29 -> 0 | D10: Control | E10: =+E8-B16 -> -2692160.8 | F10: * Debe ser Cero.
A11: Haber Sistema no conciliado | B11: =+'4. Conciliación'!E29 -> 0 | F11: * Cambiar de color si no es cero.
A12: Impuestos y Comisiones | B12: =+B33 -> 5726859
B14: =+B7+B8-B9+B10-B11-B12 -> -104367.5
A16: Saldo Final s/ Banco (Extracto) | B16: 2692160.8
A17: ⚠ DIFERENCIA EN SALDO FINAL | B17: =+B16-B14 -> 2796528.3
A19: CONCILIACIÓN
A20: Movimientos conciliados | B20: 327
A21: Con diferencia de monto | B21: 3
A22: Solo en banco (pendientes) | B22: 79
A23: Solo en sistema (pendientes) | B23: 28
A25: GASTOS BANCARIOS E IMPUESTOS
A26: RET_SIRCREB | B26: 2763039.1 | C26: 20 movimientos
A27: RET_IIBB_TUCUMAN | B27: 254212.33 | C27: 20 movimientos
A28: LEY25413_DEBITO | B28: 985573.82 | C28: 21 movimientos
A29: LEY25413_CREDITO | B29: 1420037.6 | C29: 23 movimientos
A30: COMISION | B30: 239074.83 | C30: 59 movimientos
A31: PERC_IIBB | B31: 9090.99 | C31: 8 movimientos
A32: IVA | B32: 55830.39 | C32: 69 movimientos
A33: TOTAL GASTOS | B33: 5726859

Sheet 1. Auditoría Banco
A1: AUDITORÍA: MOVIMIENTOS DETECTADOS EN BANCO - Web
A3: Saldo Anterior detectado: $ 5,622,491.49 | D3: 5622491
A5: Fecha | B5: Concepto Original | C5: Débito | D5: Crédito | E5: Descripción/Ref | F5: Clasificación Motor
B7: TOTALES | C7: =SUM(C6:C6) -> 0 | D7: =SUM(D6:D6) -> 0

Sheet 2. Auditoría Sistema
A1: AUDITORÍA: MOVIMIENTOS DETECTADOS EN SISTEMA - Web
A3: Fecha | B3: Documento/Ref | C3: Concepto Original | D3: Detalle | E3: Debe | F3: Haber
D7: TOTALES | E7: =SUM(E4:E6) -> 0 | F7: =SUM(F4:F6) -> 0

Sheet 3. Detalle Impuestos
A1: DETALLE DIARIO DE IMPUESTOS Y GASTOS BANCARIOS - Web
A3: COMISION
A4: Fecha | B4: Concepto Banco | C4: Referencia / Detalle | D4: Monto
A5: 46084 | B5: Comision compensacion cheques cfu | D5: 18463.2
A6: 46084 | B6: Comision transf otros bcos canales | C6: Comision transferencias | D6: 1485
A7: 46086 | B7: Comision transf otros bcos canales | C7: Comision transferencias | D7: 120
A8: 46086 | B8: Comision transf otros bcos canales | C8: Comision transferencias | D8: 120
A9: 46086 | B9: Comision transf otros bcos canales | C9: Comision transferencias | D9: 720
A10: 46086 | B10: Comision transf otros bcos canales | C10: Comision transferencias | D10: 1485
A11: 46086 | B11: Comision transf otros bcos canales | C11: Comision transferencias | D11: 1485
A12: 46086 | B12: Comision transf otros bcos canales | C12: Comision transferencias | D12: 1485
A13: 46086 | B13: Comision transf otros bcos canales | C13: Comision transferencias | D13: 1485
A14: 46090 | B14: Comision compensacion cheques cfu | D14: 4381.07
A15: 46090 | B15: Comision transf otros bcos canales | C15: Comision transferencias | D15: 720
A16: 46091 | B16: Comision compensacion cheques cfu | D16: 8260
A17: 46091 | B17: Comision transf otros bcos canales | C17: Comision transferencias | D17: 315
A18: 46091 | B18: Comision transf otros bcos canales | C18: Comision transferencias | D18: 315
A19: 46091 | B19: Comision transf otros bcos canales | C19: Comision transferencias | D19: 315
A20: 46091 | B20: Comision transf otros bcos canales | C20: Comision transferencias | D20: 720
A21: 46091 | B21: Comision transf otros bcos canales | C21: Comision transferencias | D21: 720
A22: 46091 | B22: Comision transf otros bcos canales | C22: Comision transferencias | D22: 720
A23: 46091 | B23: Comision transf otros bcos canales | C23: Comision transferencias | D23: 720
A24: 46091 | B24: Comision transf otros bcos canales | C24: Comision transferencias | D24: 720
A25: 46091 | B25: Comision transf otros bcos canales | C25: Comision transferencias | D25: 720
A26: 46091 | B26: Comision transf otros bcos canales | C26: Comision transferencias | D26: 1485
A27: 46091 | B27: Comision transf otros bcos canales | C27: Comision transferencias | D27: 1485
A28: 46091 | B28: Comision transf otros bcos canales | C28: Comision transferencias | D28: 1485
A29: 46093 | B29: Comision compensacion cheques cfu | D29: 13904.16
A30: 46093 | B30: Comision transf otros bcos canales | C30: Comision transferencias | D30: 720
A31: 46093 | B31: Comision transf otros bcos canales | C31: Comision transferencias | D31: 1485
A32: 46093 | B32: Comision transf otros bcos canales | C32: Comision transferencias | D32: 1485
A33: 46093 | B33: Comision transf otros bcos canales | C33: Comision transferencias | D33: 1485
A34: 46093 | B34: Comision transf otros bcos canales | C34: Comision transferencias | D34: 1485
A35: 46093 | B35: Comision transf otros bcos canales | C35: Comision transferencias | D35: 1485
A36: 46094 | B36: Comision transf otros bcos canales | C36: Comision transferencias | D36: 1485
A37: 46098 | B37: Comision transf otros bcos canales | C37: Comision transferencias | D37: 315
A38: 46098 | B38: Comision transf otros bcos canales | C38: Comision transferencias | D38: 720
A39: 46098 | B39: Comision transf otros bcos canales | C39: Comision transferencias | D39: 720
A40: 46098 | B40: Comision transf otros bcos canales | C40: Comision transferencias | D40: 720
A41: 46098 | B41: Comision transf otros bcos canales | C41: Comision transferencias | D41: 1485
A42: 46099 | B42: Comision compensacion cheques cfu | D42: 41472.96
A43: 46099 | B43: Comision transf otros bcos canales | C43: Comision transferencias | D43: 1485
A44: 46100 | B44: Comision compensacion cheques cfu | D44: 2835
A45: 46100 | B45: Comision transf otros bcos canales | C45: Comision transferencias | D45: 720
A46: 46100 | B46: Comision transf otros bcos canales | C46: Comision transferencias | D46: 720
A47: 46100 | B47: Comision transf otros bcos canales | C47: Comision transferencias | D47: 720
A48: 46100 | B48: Comision transf otros bcos canales | C48: Comision transferencias | D48: 1485
A49: 46101 | B49: Comision compensacion cheques cfu | D49: 2835
A50: 46106 | B50: Comision transf otros bcos canales | C50: Comision transferencias | D50: 720
A51: 46106 | B51: Comision transf otros bcos canales | C51: Comision transferencias | D51: 720
A52: 46106 | B52: Comision transf otros bcos canales | C52: Comision transferencias | D52: 1485
A53: 46106 | B53: Comision transf otros bcos canales | C53: Comision transferencias | D53: 1485
A54: 46106 | B54: Comision transf otros bcos canales | C54: Comision transferencias | D54: 1485
A55: 46106 | B55: Comision transf otros bcos canales | C55: Comision transferencias | D55: 1485
A56: 46106 | B56: Comision transf otros bcos canales | C56: Comision transferencias | D56: 1485
A57: 46106 | B57: Comision transf otros bcos canales | C57: Comision transferencias | D57: 1485
A58: 46107 | B58: Comision compensacion cheques cfu | D58: 24013.44
A59: 46111 | B59: Comision por servicio de cuenta | D59: 57500
A60: 46111 | B60: Comision servicio cuenta dolares | D60: 13825
A61: 46111 | B61: Comision transf otros bcos canales | C61: Comision transferencias | D61: 720
A62: 46111 | B62: Comision transf otros bcos canales | C62: Comision transferencias | D62: 1485
A63: 46111 | B63: Comision transf otros bcos canales | C63: Comision transferencias | D63: 1485
C64: TOTAL COMISION | D64: =SUM(D5:D63) -> 239074.83
A66: IVA
A67: Fecha | B67: Concepto Banco | C67: Referencia / Detalle | D67: Monto
A68: 46084 | B68: Iva 21% reg de transfisc ley27743 | D68: 3877.27
A69: 46084 | B69: Iva percepcion rg 2408 | D69: 553.9
A70: 46084 | B70: Iva 21% reg de transfisc ley27743 | D70: 311.85
A71: 46086 | B71: Iva 21% reg de transfisc ley27743 | D71: 25.2
A72: 46086 | B72: Iva 21% reg de transfisc ley27743 | D72: 25.2
A73: 46086 | B73: Iva 21% reg de transfisc ley27743 | D73: 151.2
A74: 46086 | B74: Iva 21% reg de transfisc ley27743 | D74: 311.85
A75: 46086 | B75: Iva 21% reg de transfisc ley27743 | D75: 311.85
A76: 46086 | B76: Iva 21% reg de transfisc ley27743 | D76: 311.85
A77: 46086 | B77: Iva 21% reg de transfisc ley27743 | D77: 311.85
A78: 46090 | B78: Iva 21% reg de transfisc ley27743 | D78: 920.02
A79: 46090 | B79: Iva percepcion rg 2408 | D79: 131.43
... A128: 46107 | B128: Iva 21% reg de transfisc ley27743 | D128: 5042.82
A129: 46107 | B129: Iva percepcion rg 2408 | D129: 720.4 | E129: * Las Percepciones deben estar separadas de la agrupacion IVA. Es otra como IVA Percepcion
A130: 46111 | B130: Iva 21% reg de transfisc ley27743 | D130: 12075
A131: 46111 | B131: Iva percepcion rg 2408 | D131: 1725
A132: 46111 | B132: Iva 21% reg de transfisc ley27743 | D132: 2903.25
A133: 46111 | B133: Iva percepcion rg 2408 | D133: 414.75
A134: 46111 | B134: Iva 21% reg de transfisc ley27743 | D134: 151.2
A135: 46111 | B135: Iva 21% reg de transfisc ley27743 | D135: 311.85
A136: 46111 | B136: Iva 21% reg de transfisc ley27743 | D136: 311.85
C137: TOTAL IVA | D137: =SUM(D68:D136) -> 55830.39
A139: LEY25413 CREDITO
A140: Fecha | B140: Concepto Banco | C140: Referencia / Detalle | D140: Monto
A141: 46083 | B141: Impuesto ley 25.413 credito 0,6% | D141: 16579.78
A142: 46084 | B142: Impuesto ley 25.413 credito 0,6% | D142: 103408.22
A143: 46085 | B143: Impuesto ley 25.413 credito 0,6% | D143: 1849.17
A144: 46086 | B144: Impuesto ley 25.413 credito 0,6% | D144: 31677.38
A145: 46087 | B145: Impuesto ley 25.413 credito 0,6% | D145: 41923.59
A146: 46090 | B146: Impuesto ley 25.413 credito 0,6% | D146: 27099.32
A147: 46091 | B147: Impuesto ley 25.413 credito 0,6% | D147: 627894.27
A148: 46092 | B148: Impuesto ley 25.413 credito 0,6% | D148: 28560.46
A149: 46093 | B149: Impuesto ley 25.413 credito 0,6% | D149: 133806.09
A150: 46094 | B150: Impuesto ley 25.413 credito 0,6% | D150: 24017.86
A151: 46094 | B151: Impuesto ley 25.413 credito 0,6% | C151: Cta orig: 195-032021/8 - base impo. usd 1.730,83 | D151: 14532
...

Sheet 4. Conciliación
A1: CONCILIACIÓN BANCARIA - Web
A2: INSTRUMENTAL PASTEUR SRL Desde: 28/02/26
D3: *No cruces las columnas para conciliar. Es importante que los debitos del banco se concilian con el Haber del mayor y los Creditos con el Debe.
A4: 1. CRUCE DE MOVIMIENTOS (Banco vs Sistema)
A5: Fecha Banco | B5: Monto Banco | C5: Conc. Banco | D5: Fecha Sist. | E5: Monto Sist. | F5: Ref. Sist. | G5: Dif. $ | H5: Dif. Días | I5: Nivel Cierre | J5: Estado
B8: =SUM(B6:B7) -> 0 | E8: =SUM(E6:E7) -> 0 | G8: =SUM(G6:G7) -> 0 | I8: *Marcar los que no son exactos.
H9: *Marcar con color los que tienen diferencia
G10: *Marcar con color los que tienen diferencia
A11: SOLO EN BANCO (79 movimientos sin match)
A12: Fecha | B12: Concepto | C12: Tipo Automático | D12: Débito | E12: Crédito
A17: TOTAL SOLO EN BANCO | D17: =SUM(D13:D16) -> 0 | E17: =SUM(E13:E16) -> 0
C19: Control | D19: =+B8+E17-D17 -> 0 | E19: =+'1. Auditoría Banco'!D7-'1. Auditoría Banco'!C7 -> 0
E20: =+E19-D19 -> 0 | F20: * tiene que ser 0
A23: SOLO EN SISTEMA (28 movimientos sin match)
A24: Fecha | B24: Ref. | C24: Concepto | D24: Debe | E24: Haber
D29: =SUM(D25:D28) -> 0 | E29: =SUM(E25:E28) -> 0

Sheet 5. Conceptos Agrupados
A1: AGRUPACIÓN TOTAL POR CONCEPTOS BANCARIOS - Web
A3: Tipo Clasificación | B3: Concepto Exacto | C3: Cant. | D3: Total Débitos | E3: Total Créditos
A4: COMISION | B4: COMISION COMPENSACION CHEQUES CFU | C4: 8 | D4: 116164.83 | E4: 0
A5: COMISION | B5: COMISION POR SERVICIO DE CUENTA | C5: 1 | D5: 57500 | E5: 0
A6: COMISION | B6: COMISION TRANSF OTROS BCOS CANALES | C6: 49 | D6: 51585 | E6: 0
A7: COMISION | B7: COMISION SERVICIO CUENTA DOLARES | C7: 1 | D7: 13825 | E7: 0
A8: DEB_AUTOMATICO | B8: DEBITO AUTOMATICO | C8: 14 | D8: 6815769.2 | E8: 0
A9: HABERES | B9: PAGO DE HONORARIOS | C9: 4 | D9: 6709500 | E9: 0
A10: IVA | B10: IVA 21% REG DE TRANSFISC LEY27743 | C10: 59 | D10: 50205.7 | E10: 0
A11: IVA | B11: IVA PERCEPCION RG 2408 | C11: 10 | D11: 5624.69 | E11: 0
A12: LEY25413_CREDITO | B12: IMPUESTO LEY 25.413 CREDITO 0,6% | C12: 23 | D12: 1420037.6 | E12: 0
A13: LEY25413_DEBITO | B13: IMPUESTO LEY 25.413 DEBITO 0,6% | C13: 21 | D13: 985573.82 | E13: 0
A14: OTRO | B14: SUSCRIPCION FONDOS COMUNES INVERS | C14: 16 | D14: 110500000 | E14: 110000000
A15: OTRO | B15: TRANSFERENCIA POR SISTEMA MEP | C15: 1 | D15: 100000000 | E15: 0
... A42: RET_SIRCREB | B42: REGIMEN DE RECAUDACION SIRCREB R | C42: 1 | D42: 47495.65 | E42: 0
B43: TOTALES | D43: =SUM(D4:D42) -> 4.4436573e+08 | E43: =SUM(E4:E42) -> 4.7303043e+08
